[{"name": "Johan Fredrik I av Sachsen", "jobs": ["Q2478141"], "first_paragraph": "Johan Fredrik I av Sachsen (\"den \u00e4delmodige\"), f\u00f6dd 30 juni 1503 i Torgau, d\u00f6d 3 mars 1554 i Weimar, var fr\u00e5n 1532 till 1547 kurfurste av Sachsen och fr\u00e5n 1547 till 1554 hertig av Sachsen. Han var son till kurfurst Johan den st\u00e5ndaktige.", "id": "Q506182"}, {"name": "James Taylor", "jobs": ["Q488205", "Q639669", "Q36180", "Q855091"], "first_paragraph": "James Vernon Taylor, f\u00f6dd 12 mars 1948 i Boston, Massachusetts, \u00e4r en amerikansk s\u00e5ngare, l\u00e5tskrivare och gitarrist. Han hade under 1970-talet stora framg\u00e5ngar som singer-songwriter, med l\u00e5tar som \"Sunny Skies\", \"Country Road\" och \"Sweet Baby James\".", "id": "Q310300"}, {"name": "Manfred Chobot", "jobs": ["Q36180"], "first_paragraph": "Manfred Chobot, f\u00f6dd 3 maj 1947 i Wien, \u00e4r en \u00f6sterrikisk poet och f\u00f6rfattare. ", "id": "Q112230"}, {"name": "Ferdinand von Lindemann", "jobs": ["Q170790", "Q1622272"], "first_paragraph": "Carl Louis Ferdinand von Lindemann, f\u00f6dd 12 april 1852 i Hannover, d\u00f6d 6 mars 1939 i M\u00fcnchen, var en tysk matematiker.", "id": "Q77203"}, {"name": "Georges Boulanger", "jobs": ["Q82955", "Q47064"], "first_paragraph": "Georges Ernest Jean-Marie Boulanger, f\u00f6dd 29 april 1837 i Rennes, Frankrike, d\u00f6d 30 september 1891 i Ixelles n\u00e4ra Bryssel, Belgien, var en fransk milit\u00e4r och reaktion\u00e4r politiker, som gjorde en m\u00e4rklig politisk karri\u00e4r och som 1889 var ytterst n\u00e4ra att g\u00f6ra sig till diktator.", "id": "Q315747"}, {"name": "Jeremy Rifkin", "jobs": ["Q188094", "Q2306091", "Q36180", "Q1622272"], "first_paragraph": "Jeremy Rifkin, f\u00f6dd 1945 i Denver, Colorado, \u00e4r en amerikansk nationalekonom, f\u00f6rfattare och debatt\u00f6r. Han har de senaste 30 \u00e5ren skrivit 20 b\u00f6cker om inverkan av teknik och vetenskap p\u00e5 ekonomi, arbetsmarknaden, samh\u00e4llet, milj\u00f6n och h\u00e5llbar utveckling. Flera av b\u00f6ckerna har blivit internationella bestsellers och \u00f6versatts till alla st\u00f6rre spr\u00e5k. ", "id": "Q505154"}, {"name": "Sebasti\u00e1n Leto", "jobs": ["Q937857"], "first_paragraph": "Sebasti\u00e1n Eduardo Leto, f\u00f6dd 30 augusti 1986, \u00e4r en argentinsk fotbollsspelare som spelar f\u00f6r Panathinaikos. ", "id": "Q371594"}, {"name": "Simphiwe Dana", "jobs": ["Q177220", "Q36834"], "first_paragraph": "Simphiwe Dana, f\u00f6dd 1980, \u00e4r sydafrikansk pops\u00e5ngerska som sjunger p\u00e5 xhosa. 2005 vann hon pris som b\u00e4sta nykomling vid South African Music Awards med sitt debutalbum \"Zandisile\". Tv\u00e5 \u00e5r senare blev hon utn\u00e4mnd till b\u00e4sta kvinnliga artist vid samma musikgala. Dana \u00e4r en internationell artist som f\u00f6rutom spelningar i Sydafrika ocks\u00e5 har gjort flera framtr\u00e4danden i Europa. ", "id": "Q448917"}, {"name": "Shaquille O'Neal", "jobs": ["Q3665646", "Q33999", "Q2252262", "Q2986228", "Q43845", "Q7301138", "Q3282637", "Q578109", "Q177220", "Q15077007", "Q388513", "Q10800557"], "first_paragraph": "Shaquille Rashaun O'Neal, f\u00f6dd 6 mars 1972 i Newark, New Jersey, \u00e4ven k\u00e4nd under smeknamnet \"Shaq\", \u00e4r en amerikansk f\u00f6re detta basketspelare och f\u00f6re detta rappare. Han spelade p\u00e5 positionen som center och \u00e4r, med sina 2,16 m och 147 kg en av NBA:s tyngsta spelare n\u00e5gonsin.", "id": "Q169452"}, {"name": "Eglantyne Jebb", "jobs": ["Q12362622"], "first_paragraph": "Eglantyne Jebb, f\u00f6dd 25 augusti 1876 i Ellesmere, Shropshire, d\u00f6d 17 december 1928 i Gen\u00e8ve, Schweiz, var en brittisk filantrop och grundare av R\u00e4dda barnen. Hennes smeknamn var \"vita l\u00e5gan\", d\u00e5 hon brann med en het l\u00e5ga f\u00f6r barns r\u00e4ttigheter genom hela livet.", "id": "Q258887"}, {"name": "Jackie McNamara", "jobs": ["Q937857", "Q628099"], "first_paragraph": "Jackie McNamara Junior, f\u00f6dd den 24 oktober 1973 i Glasgow, \u00e4r en skotsk manager och f\u00f6re detta fotbollsspelare. Han \u00e4r mest k\u00e4nd f\u00f6r att ha representerat Celtic mellan 1995 och 2005. Han har \u00e4ven 33 landskamper f\u00f6r Skottland p\u00e5 meritlistan. Sedan januari 2013 \u00e4r han manager f\u00f6r Dundee United.", "id": "Q461705"}]