[{"name": "Lee Strasberg", "jobs": ["Q33999", "Q3455803", "Q37226"], "first_paragraph": "Lee Strasberg, ursprungligen Israel Strassberg, f\u00f6dd 17 november 1901 i Budaniv, Ukraina (d\u00e5varande \u00d6sterrike-Ungern), d\u00f6d 17 februari 1982 i New York i New York i USA, var en amerikansk teaterregiss\u00f6r, teaterpedagog och sk\u00e5despelare.", "id": "Q297945"}, {"name": "Bj\u00f8rg Vik", "jobs": ["Q482980", "Q4853732", "Q1930187", "Q36180"], "first_paragraph": "Bj\u00f8rg Vik, f\u00f6dd 11 september 1935 i Oslo, d\u00f6d 7 januari 2018, var en norsk f\u00f6rfattare och dramatiker. ", "id": "Q455323"}, {"name": "Benedictus XIV", "jobs": ["Q250867"], "first_paragraph": "Benedictus XIV, f\u00f6dd Prospero Lorenzo Lambertini 31 mars 1675 i Bologna, d\u00f6d 3 maj 1758 i Rom, var p\u00e5ve fr\u00e5n den 17 augusti 1740.", "id": "Q126711"}, {"name": "Carlo Goldoni", "jobs": ["Q214917", "Q36180", "Q8178443", "Q28389", "Q333634", "Q1209498", "Q482980"], "first_paragraph": "Carlo Goldoni, f\u00f6dd 25 februari 1707 i Venedig, d\u00f6d 6 februari 1793 i Paris, var en venetiansk pj\u00e4sf\u00f6rfattare.", "id": "Q165534"}, {"name": "Claudio Caniggia", "jobs": ["Q937857"], "first_paragraph": "Claudio Caniggia, f\u00f6dd 9 januari 1967 i Buenos Aires i Argentina, \u00e4r en argentinsk f.d. fotbollsspelare (h\u00f6gerytter).", "id": "Q270890"}, {"name": "Fulgencia Romay", "jobs": ["Q4009406"], "first_paragraph": "Fulgencia Romay, f\u00f6dd den 16 januari 1944 i Luyan\u00f3, Kuba, \u00e4r en kubansk friidrottare inom kortdistansl\u00f6pning.", "id": "Q454655"}, {"name": "Sambor II av Pommerellen", "jobs": ["Q2478141"], "first_paragraph": "Sambor II, f\u00f6dd 1206, d\u00f6d 1278 eller 1279, var hertig av Pommerellen i Polen. Han var gift med Mechtild av Mecklenburg och fick med henne dottern Margareta Sambiria (f\u00f6dd 1230, d\u00f6d 1282). N\u00e5gon g\u00e5ng under 1252 eller 1253 flyttades huvudstaden i hertigd\u00f6met fr\u00e5n Lubiszewo till Tczew och p\u00e5 Sambors uppdrag b\u00f6rjade man d\u00e4r n\u00e5gong g\u00e5ng mellan 1252 och 1255 ett slot. Det fick fyra flyglar och en mindre borgg\u00e5rd samt omgavs av en f\u00f6rsvarsmur och en vallgrav. Sambor gav \u00e4ven till\u00e5telse till att stadens f\u00f6rsta r\u00e5d bildades 1258 och tv\u00e5 \u00e5r senare f\u00f6rl\u00e4nade han ocks\u00e5 stadsprivilegium \u00e5t Tczew.", "id": "Q696738"}, {"name": "John Simm", "jobs": ["Q33999", "Q2259451", "Q10800557"], "first_paragraph": "John Simm, f\u00f6dd 1970 i Leeds, England, \u00e4r en brittisk sk\u00e5despelare. Han har bland annat spelat huvudroller i de brittiska TV-produktionerna The Lakes, Den tredje makten och Life on Mars. Han har \u00e4ven medverkat i Spaced, Crime and Punishment och Doctor Who.", "id": "Q443327"}, {"name": "Veronika V\u00edtkov\u00e1", "jobs": ["Q16029547"], "first_paragraph": "Veronika V\u00edtkov\u00e1, f\u00f6dd 9 december 1988 i Vrchlab\u00ed, \u00e4r en tjeckisk skidskytt.", "id": "Q271744"}, {"name": "Otmar Issing", "jobs": ["Q188094", "Q806798", "Q36180", "Q1622272"], "first_paragraph": "Otmar Issing, f\u00f6dd 27 mars 1936 i W\u00fcrzburg, Tyskland, \u00e4r en tysk ekonom (professor). Han var medlem i Deutsche Bundesbank - Tysklands centralbank (1990\u20131998) och Europeiska central banken(ECB) (1998\u20132006). ", "id": "Q67047"}, {"name": "Rudolf Abel", "jobs": ["Q9352089", "Q392651", "Q47064"], "first_paragraph": "Rudolf Abel, eg. Vilyam August (Genrikhovich) Fisher, f\u00f6dd 11 juli 1903 i Newcastle-upon-Tyne, Storbritannien, d\u00f6d 15 november 1971 i Moskva (lungcancer), var en sovjetisk spion och \u00f6verste i KGB.", "id": "Q181538"}]