[{"name": "Audrey Landers", "jobs": ["Q33999", "Q177220", "Q639669", "Q10798782", "Q10800557"], "first_paragraph": "Audrey Landers, f\u00f6dd Audrey Hamburg 18 juli 1956 i Philadelphia, Pennsylvania, USA, \u00e4r en amerikansk sk\u00e5despelerska och s\u00e5ngerska. ", "id": "Q267914"}, {"name": "Chen Maiping", "jobs": ["Q36180", "Q333634"], "first_paragraph": "Chen Maiping (traditionell kinesiska: \u9673\u9081\u5e73; f\u00f6renklad kinesiska: \u9648\u8fc8\u5e73; pinyin: Ch\u00e9n M\u00e0ip\u00edng), f\u00f6dd 4 november 1952 i Changshu i Jiangsuprovinsen, \u00e4r en kinesisk f\u00f6rfattare och poet bosatt i Sverige, k\u00e4nd under pseudonymen Wan Zhi (\u4e07\u4e4b). Han har skrivit fr\u00e4mst noveller och har \u00e4ven \u00f6versatt litteratur fr\u00e5n engelska och svenska till kinesiska.", "id": "Q716757"}, {"name": "Ferdinand Kauer", "jobs": ["Q36834", "Q1259917", "Q486748", "Q158852"], "first_paragraph": "Ferdinand Kauer, f\u00f6dd 18 januari 1751 i Kleintajax vid Znaim, d\u00f6d 13 april 1831 i Wien, var en \u00f6sterrikisk tons\u00e4ttare. ", "id": "Q347096"}, {"name": "Gerald P. Carr", "jobs": ["Q189290", "Q11631", "Q81096", "Q15895020"], "first_paragraph": "Gerald P. Carr, f\u00f6dd 22 augusti 1932 \u00e4r en amerikansk astronaut uttagen i astronautgrupp 5 den 4 april 1966.", "id": "Q644837"}, {"name": "Anton Lander", "jobs": ["Q11774891"], "first_paragraph": "Anton Lander, f\u00f6dd 24 april 1991 i Timr\u00e5, \u00e4r en svensk ishockeyspelare som spelar centerforward som spelar f\u00f6r AK Bars Kazan i KHL. Han har tidigare spelat f\u00f6r Edmonton Oilers i NHL och Timr\u00e5 IK i Sverige.", "id": "Q591400"}, {"name": "Katharina Henot", "jobs": [], "first_paragraph": "Katharina Henot, f\u00f6dd 1570, d\u00f6d i K\u00f6ln 19 maj 1627, var postm\u00e4stare i staden K\u00f6ln i Tyskland. Hon var Tysklands kanske f\u00f6rsta postm\u00e4stare av sitt k\u00f6n. Hon avr\u00e4ttades f\u00f6r h\u00e4xeri och tillh\u00f6r det mest k\u00e4nda offret f\u00f6r h\u00e4xprocesserna i sin hemtrakt, och \u00e4ven ett av de mest k\u00e4nda i Tyskland. ", "id": "Q547021"}, {"name": "Merton Miller", "jobs": ["Q188094"], "first_paragraph": "Merton Howard \"Mert\" Miller, f\u00f6dd 16 maj 1923 i Boston, Massachusetts, d\u00f6d 3 juni 2000 i Chicago, Illinois, var en amerikansk nationalekonom som bel\u00f6nades med Sveriges Riksbanks pris i ekonomisk vetenskap till Alfred Nobels minne 1990. Han invaldes 1992 som utl\u00e4ndsk ledamot av svenska Ingenj\u00f6rsvetenskapsakademien.", "id": "Q157255"}, {"name": "Rudolf Nadolny", "jobs": ["Q193391", "Q185351"], "first_paragraph": "Rudolf Nadolny, f\u00f6dd 12 juli 1873, d\u00f6d 18 maj 1953, var en tysk diplomat.", "id": "Q216765"}, {"name": "Sverker \u00c5str\u00f6m", "jobs": ["Q193391", "Q947873"], "first_paragraph": "Carl Sverker \u00c5str\u00f6m, f\u00f6dd 30 december 1915 i Uppsala, d\u00f6d 26 juni 2012 i Stockholm,, var en svensk diplomat och ambassad\u00f6r. Han var FN-ambassad\u00f6r 1964-1970, kabinettssekreterare vid Utrikesdepartementet 1972-1977 samt ambassad\u00f6r i Paris 1978-1982.", "id": "Q683902"}, {"name": "Renny Harlin", "jobs": ["Q2526255", "Q3282637", "Q1208175"], "first_paragraph": "Renny Harlin, eg. Lauri Mauritz Harjola, f\u00f6dd 15 mars 1959 i Riihim\u00e4ki, Finland, \u00e4r en finl\u00e4ndsk filmregiss\u00f6r och filmproducent. ", "id": "Q318712"}, {"name": "John Battle", "jobs": ["Q82955"], "first_paragraph": "John Battle, f\u00f6dd 26 april 1951, \u00e4r en brittisk Labourpolitiker. Han var parlamentsledamot f\u00f6r valkretsen Leeds West 1987-2010.", "id": "Q337561"}]