[{"name": "Venedikt Jerofejev", "jobs": ["Q36180"], "first_paragraph": "Venedikt Jerofejev (\u0412\u0435\u043d\u0435\u0434\u0438\u043a\u0442 \u0415\u0440\u043e\u0444\u0435\u0435\u0432), f\u00f6dd 24 oktober 1938 i Tjupa, d\u00f6d 11 maj 1990 i Moskva, var en rysk f\u00f6rfattare.", "id": "Q366503"}, {"name": "Adolfo Bartoli", "jobs": ["Q169470", "Q1622272"], "first_paragraph": "Adolfo Bartoli kan syfta på:", "id": "Q10401434"}, {"name": "Chris Barnes", "jobs": ["Q177220", "Q7042855"], "first_paragraph": "Chris Barnes, f\u00f6dd 29 december 1967, \u00e4r en amerikansk sångare som gjort sig k\u00e4nd f\u00f6r att vara en av grundarna av death metal-bandet Cannibal Corpse samt f\u00f6r sitt arbete med Six Feet Under.", "id": "Q437476"}, {"name": "Jacopo Sadoleto", "jobs": ["Q250867"], "first_paragraph": "Jacopo Sadoleto, f\u00f6dd den 12 juli 1477 i Modena, d\u00f6d den 18 oktober 1547 i Rom, var en italiensk kardinal.", "id": "Q682478"}, {"name": "Antoine Galland", "jobs": ["Q175151"], "first_paragraph": "Jean Antoine Galland, f\u00f6dd den 4 april 1646, d\u00f6d den 19 februari 1715, var en fransk orientalist.", "id": "Q319399"}, {"name": "Laura Trott", "jobs": ["Q15117395", "Q2309784"], "first_paragraph": "Laura Rebecca Trott, f\u00f6dd 24 april 1992 i Cheshunt, \u00e4r en brittisk bancyklist. Under olympiska sommarspelen 2012 tog hon två guld, i lagf\u00f6rf\u00f6ljelse och omnium. Trott blev d\u00e4rmed v\u00e4rlds-, europa-, samt olympisk m\u00e4stare i båda grenarna under s\u00e4songen 2011-2012.", "id": "Q272598"}, {"name": "Woody Harrelson", "jobs": ["Q10798782", "Q10800557", "Q214917", "Q2259451", "Q13235160", "Q3387717", "Q2526255", "Q28389"], "first_paragraph": "Woodrow Tracy \"Woody\" Harrelson, f\u00f6dd 23 juli 1961 i Midland, Texas, \u00e4r en amerikansk skådespelare som slog igenom i TV-serien Skål och \u00e4r bland annat k\u00e4nd från filmer som Natural Born Killers, Wag the Dog, Zombieland och  Larry Flynt - skandalernas man.", "id": "Q201279"}, {"name": "Kim Hunter", "jobs": ["Q33999", "Q2259451", "Q10798782", "Q10800557"], "first_paragraph": "Kim Hunter, f\u00f6dd Janet Cole 12 november 1922 i Detroit, Michigan, d\u00f6d 11 september 2002 i New York, var en amerikansk skådespelare.", "id": "Q59824"}, {"name": "Christoph Bechmann", "jobs": ["Q10843263"], "first_paragraph": "Christoph Bechmann, f\u00f6dd den 23 november 1971 i Speyer, Tyskland, \u00e4r en tysk landhockeyspelare.", "id": "Q98080"}, {"name": "Charles Mackerras", "jobs": ["Q158852", "Q16003954", "Q36834", "Q1198887"], "first_paragraph": "Sir Alan Charles Maclaurin Mackerras, f\u00f6dd 17 november 1925 i Schenectady, New York, d\u00f6d 14 juli 2010 i London, var en australisk dirigent. Han var en erk\u00e4nd auktoritet n\u00e4r det g\u00e4ller interpretation av operor av Jan\u00e1\u010dek och Mozart samt operetter av Gilbert & Sullivan.", "id": "Q322172"}, {"name": "Colin Burgon", "jobs": ["Q82955"], "first_paragraph": "Colin Burgon, f\u00f6dd 22 april 1948 i Leeds, \u00e4r en brittisk Labourpolitiker. Han var parlamentsledamot f\u00f6r valkretsen Elmet från valet 1997 till valet 2010.", "id": "Q337923"}]